jumpyng/__init__.py
jumpyng/algorithm.py
jumpyng/dlchelper.py
jumpyng/utils.py
jumpyng/validation.py
jumpyng/visualization.py
jumpyng-0.1.9.dist-info/METADATA
jumpyng-0.1.9.dist-info/WHEEL
jumpyng-0.1.9.dist-info/top_level.txt
jumpyng-0.1.9.dist-info/RECORD
